sagemaker/__init__.py
sagemaker/core/__init__.py
sagemaker/core/_studio.py
sagemaker/core/_version.py
sagemaker/core/accept_types.py
sagemaker/core/analytics.py
sagemaker/core/base_deserializers.py
sagemaker/core/base_serializers.py
sagemaker/core/collection.py
sagemaker/core/common_utils.py
sagemaker/core/config_schema.py
sagemaker/core/constants.py
sagemaker/core/content_types.py
sagemaker/core/deprecations.py
sagemaker/core/drift_check_baselines.py
sagemaker/core/enums.py
sagemaker/core/environment_variables.py
sagemaker/core/exceptions.py
sagemaker/core/fw_utils.py
sagemaker/core/git_utils.py
sagemaker/core/hyperparameters.py
sagemaker/core/image_uris.py
sagemaker/core/inference_config.py
sagemaker/core/inputs.py
sagemaker/core/instance_group.py
sagemaker/core/instance_types.py
sagemaker/core/instance_types_gpu_info.py
sagemaker/core/iterators.py
sagemaker/core/job.py
sagemaker/core/lambda_helper.py
sagemaker/core/logs.py
sagemaker/core/metadata_properties.py
sagemaker/core/metric_definitions.py
sagemaker/core/model_life_cycle.py
sagemaker/core/model_metrics.py
sagemaker/core/model_registry.py
sagemaker/core/model_uris.py
sagemaker/core/network.py
sagemaker/core/parameter.py
sagemaker/core/payloads.py
sagemaker/core/processing.py
sagemaker/core/resource_requirements.py
sagemaker/core/resources.py
sagemaker/core/script_uris.py
sagemaker/core/serverless_inference_config.py
sagemaker/core/session_settings.py
sagemaker/core/training_compiler_config.py
sagemaker/core/transformer.py
sagemaker/core/user_agent.py
sagemaker/core/apiutils/__init__.py
sagemaker/core/apiutils/_base_types.py
sagemaker/core/apiutils/_boto_functions.py
sagemaker/core/apiutils/_utils.py
sagemaker/core/clarify/__init__.py
sagemaker/core/compute_resource_requirements/__init__.py
sagemaker/core/compute_resource_requirements/resource_requirements.py
sagemaker/core/config/__init__.py
sagemaker/core/config/config.py
sagemaker/core/config/config_manager.py
sagemaker/core/config/config_schema.py
sagemaker_core-2.3.0.dist-info/licenses/LICENSE
sagemaker_core-2.3.0.dist-info/METADATA
sagemaker_core-2.3.0.dist-info/WHEEL
sagemaker_core-2.3.0.dist-info/top_level.txt
sagemaker_core-2.3.0.dist-info/RECORD
