Metadata-Version: 2.4
Name: sagemaker-core
Version: 2.3.0
Summary: An python package for sagemaker core functionalities
Author-email: AWS <sagemaker-interests@amazon.com>
Project-URL: Homepage, https://github.com/aws/sagemaker-python-sdk
Classifier: Development Status :: 3 - Alpha
Classifier: Intended Audience :: Developers
Classifier: License :: OSI Approved :: Apache Software License
Classifier: Programming Language :: Python :: 3.9
Classifier: Programming Language :: Python :: 3.10
Classifier: Programming Language :: Python :: 3.11
Classifier: Programming Language :: Python :: 3.12
Requires-Python: >=3.9
License-File: LICENSE
Requires-Dist: boto3<2.0.0,>=1.42.2
Requires-Dist: pydantic<3.0.0,>=2.0.0
Requires-Dist: PyYAML<7.0,>=6.0
Requires-Dist: jsonschema<5.0.0
Requires-Dist: platformdirs<5.0.0,>=4.0.0
Requires-Dist: rich<14.0.0,>=13.0.0
Requires-Dist: mock<5.0,>4.0
Requires-Dist: importlib-metadata<7.0,>=1.4.0
Requires-Dist: typing_extensions>=4.9.0
Requires-Dist: pytz>=2021.1
Requires-Dist: requests<3.0.0,>=2.20.0
Requires-Dist: attrs>=20.3.0
Requires-Dist: packaging>=20.0
Requires-Dist: protobuf<5.0,>=3.12
Requires-Dist: pandas>=1.0.0
Requires-Dist: numpy>=1.9.0
Requires-Dist: smdebug_rulesconfig>=1.0.1
Requires-Dist: schema>=0.7.5
Requires-Dist: omegaconf>=2.1.0
Requires-Dist: torch>=1.9.0
Requires-Dist: scipy>=1.5.0
Requires-Dist: cloudpickle>=2.0.0
Requires-Dist: paramiko>=2.11.0
Requires-Dist: tblib>=1.7.0
Provides-Extra: codegen
Requires-Dist: black<25.0.0,>=24.3.0; extra == "codegen"
Requires-Dist: pandas<3.0.0,>=2.0.0; extra == "codegen"
Requires-Dist: pytest<9.0.0,>=8.0.0; extra == "codegen"
Requires-Dist: pylint<4.0.0,>=3.0.0; extra == "codegen"
Provides-Extra: test
Requires-Dist: pytest<9.0.0,>=8.0.0; extra == "test"
Requires-Dist: pytest-cov>=4.0.0; extra == "test"
Requires-Dist: pytest-xdist>=3.0.0; extra == "test"
Dynamic: license-file
